colepy/__init__.py
colepy/comte.py
colepy-0.0.1.dist-info/LICENSE
colepy-0.0.1.dist-info/METADATA
colepy-0.0.1.dist-info/WHEEL
colepy-0.0.1.dist-info/top_level.txt
colepy-0.0.1.dist-info/RECORD
